adasplash/__init__.py
adasplash/adasplash_block_mask.py
adasplash/adasplash_no_block_mask.py
adasplash/triton_entmax.py
adasplash-0.1.0.dist-info/LICENSE
adasplash-0.1.0.dist-info/METADATA
adasplash-0.1.0.dist-info/WHEEL
adasplash-0.1.0.dist-info/top_level.txt
adasplash-0.1.0.dist-info/RECORD
