Metadata-Version: 2.2
Name: adasplash
Version: 0.1.0
Summary: AdaSplash: Efficient Adaptive Sparse Attention in Triton
Home-page: https://github.com/deep-spin/adasplash
Author: Nuno Gonçalves, Marcos Treviso
Author-email: marcosvtreviso@gmail.com
Classifier: Programming Language :: Python :: 3
Classifier: License :: OSI Approved :: MIT License
Classifier: Operating System :: OS Independent
Requires-Python: >=3.8
License-File: LICENSE
Requires-Dist: torch
Requires-Dist: triton
Provides-Extra: dev
Requires-Dist: pytest; extra == "dev"
Requires-Dist: black; extra == "dev"
Requires-Dist: isort; extra == "dev"
Requires-Dist: flake8; extra == "dev"
Requires-Dist: entmax; extra == "dev"
Dynamic: author
Dynamic: author-email
Dynamic: classifier
Dynamic: description
Dynamic: description-content-type
Dynamic: home-page
Dynamic: provides-extra
Dynamic: requires-dist
Dynamic: requires-python
Dynamic: summary
